sep005_io_parquet/__init__.py
sep005_io_parquet/parquet.py
sep005_io_parquet-0.0.8.dist-info/METADATA
sep005_io_parquet-0.0.8.dist-info/WHEEL
sep005_io_parquet-0.0.8.dist-info/top_level.txt
sep005_io_parquet-0.0.8.dist-info/RECORD
