Metadata-Version: 2.4
Name: sep005_io_parquet
Version: 0.0.8
Summary: Parquet file read functions compliant with SDyPy SEP005
Home-page: https://github.com/OWI-Lab
Author: Wout Weijtjens
Author-email: wout.weijtjens@vub.be
Maintainer: Wout Weijtjens
Maintainer-email: wout.weijtjens@vub.be
License: MIT license
Keywords: io,parquet,SEP005
Classifier: Development Status :: 3 - Alpha
Classifier: Intended Audience :: Developers
Classifier: Programming Language :: Python :: 3.6
Requires-Dist: numpy>=1.11.0
Requires-Dist: sdypy-sep005>=0.1.0
Requires-Dist: pytz
Requires-Dist: pandas
Requires-Dist: pyarrow
Dynamic: author
Dynamic: author-email
Dynamic: classifier
Dynamic: description
Dynamic: home-page
Dynamic: keywords
Dynamic: license
Dynamic: maintainer
Dynamic: maintainer-email
Dynamic: requires-dist
Dynamic: summary
